{
  "type": "FeatureCollection",
  "features": [
    {
      "type": "Feature",
      "id": 1047003,
      "geometry": {
        "type": "Point",
        "coordinates": [
          153.08302099985625,
          -27.506981000394607
        ]
      },
      "properties": {
        "locality": "Camp Hill",
        "objectid": 1047003,
        "globalid": "{D5D20567-B188-4119-8445-89C05FD10ED4}",
        "sighttime": 1764640800000,
        "joeypresent": "No",
        "numberofkoala": 1,
        "koalacondifinal": "Healthy",
        "lga": "Brisbane City",
        "sighting_lat_wgs84": -27.506981000000003,
        "sighting_long_wgs84": 153.083021
      }
    },
    {
      "type": "Feature",
      "id": 1048658,
      "geometry": {
        "type": "Point",
        "coordinates": [
          153.26737608766479,
          -27.637037612190621
        ]
      },
      "properties": {
        "locality": "Redland Bay",
        "objectid": 1048658,
        "globalid": "{F4C3A5FD-D907-4838-8A72-774F50290206}",
        "sighttime": 1745280000000,
        "joeypresent": "Not Sure",
        "numberofkoala": 1,
        "koalacondifinal": "Healthy",
        "lga": "Redland City",
        "sighting_lat_wgs84": -27.63703761,
        "sighting_long_wgs84": 153.26737609
      }
    },
    {
      "type": "Feature",
      "id": 1048660,
      "geometry": {
        "type": "Point",
        "coordinates": [
          153.25191009974361,
          -27.509240799881606
        ]
      },
      "properties": {
        "locality": null,
        "objectid": 1048660,
        "globalid": "{3A895886-70C3-4601-B0EE-20C30DCF8023}",
        "sighttime": 1745291880000,
        "joeypresent": "No",
        "numberofkoala": 1,
        "koalacondifinal": "Healthy",
        "lga": "Redland City",
        "sighting_lat_wgs84": -27.509240800000001,
        "sighting_long_wgs84": 153.2519101
      }
    },
    {
      "type": "Feature",
      "id": 1042197,
      "geometry": {
        "type": "Point",
        "coordinates": [
          153.14911741430774,
          -27.748447581213338
        ]
      },
      "properties": {
        "locality": "Buccan",
        "objectid": 1042197,
        "globalid": "{99791CBA-F934-4E51-B1E0-92B1EE0333E2}",
        "sighttime": 1769898060000,
        "joeypresent": "No",
        "numberofkoala": 1,
        "koalacondifinal": "Healthy",
        "lga": "Logan City",
        "sighting_lat_wgs84": -27.748447580000001,
        "sighting_long_wgs84": 153.14911741
      }
    }
  ]
}
