{
  "type": "FeatureCollection",
  "features": [
    {
      "type": "Feature",
      "id": 1011014,
      "geometry": {
        "type": "Point",
        "coordinates": [
          153.2505771040666,
          -27.511491565018552
        ]
      },
      "properties": {
        "objectid": 1011014,
        "globalid": "{75C2D036-1422-45B0-A036-3F166EAE92D1}",
        "sighttime": 1715898240000,
        "joeypresent": "Not Sure",
        "numberofkoala": 1,
        "koalacondifinal": "Healthy",
        "has_attachment": null,
        "locality": null,
        "near_koala_habitat": null,
        "attachment_cc_lic_check": null,
        "lga": null,
        "sighting_lat_wgs84": null,
        "sighting_long_wgs84": null,
        "vetting_code": null
      }
    },
    {
      "type": "Feature",
      "id": 1011015,
      "geometry": {
        "type": "Point",
        "coordinates": [
          153.2472455715797,
          -27.511411909299923
        ]
      },
      "properties": {
        "objectid": 1011015,
        "globalid": "{EEAD80F2-FC0A-44B0-8758-EE94BDD09A58}",
        "sighttime": 1715899620000,
        "joeypresent": "Not Sure",
        "numberofkoala": 1,
        "koalacondifinal": "Healthy",
        "has_attachment": null,
        "locality": null,
        "near_koala_habitat": null,
        "attachment_cc_lic_check": null,
        "lga": null,
        "sighting_lat_wgs84": null,
        "sighting_long_wgs84": null,
        "vetting_code": null
      }
    },
    {
      "type": "Feature",
      "id": 1011016,
      "geometry": {
        "type": "Point",
        "coordinates": [
          152.85956406232677,
          -27.547610922868532
        ]
      },
      "properties": {
        "objectid": 1011016,
        "globalid": "{0D5D860A-160B-4059-A255-E7DD664BA4DB}",
        "sighttime": 1715915880000,
        "joeypresent": "No",
        "numberofkoala": 1,
        "koalacondifinal": "Healthy",
        "has_attachment": null,
        "locality": null,
        "near_koala_habitat": null,
        "attachment_cc_lic_check": null,
        "lga": null,
        "sighting_lat_wgs84": null,
        "sighting_long_wgs84": null,
        "vetting_code": null
      }
    },
    {
      "type": "Feature",
      "id": 1011017,
      "geometry": {
        "type": "Point",
        "coordinates": [
          152.8579547879875,
          -27.543056745935708
        ]
      },
      "properties": {
        "objectid": 1011017,
        "globalid": "{71BF2A0D-0CDC-4BBF-84CB-D96163F71272}",
        "sighttime": 1715915940000,
        "joeypresent": "No",
        "numberofkoala": 1,
        "koalacondifinal": "Healthy",
        "has_attachment": null,
        "locality": null,
        "near_koala_habitat": null,
        "attachment_cc_lic_check": null,
        "lga": null,
        "sighting_lat_wgs84": null,
        "sighting_long_wgs84": null,
        "vetting_code": null
      }
    },
    {
      "type": "Feature",
      "id": 1011018,
      "geometry": {
        "type": "Point",
        "coordinates": [
          152.64166668130983,
          -27.452378135894655
        ]
      },
      "properties": {
        "objectid": 1011018,
        "globalid": "{35814A2E-4EFA-435C-8B15-A4414DD057C9}",
        "sighttime": 1715919540000,
        "joeypresent": "Not Sure",
        "numberofkoala": 1,
        "koalacondifinal": "Healthy",
        "has_attachment": null,
        "locality": null,
        "near_koala_habitat": null,
        "attachment_cc_lic_check": null,
        "lga": null,
        "sighting_lat_wgs84": null,
        "sighting_long_wgs84": null,
        "vetting_code": null
      }
    },
    {
      "type": "Feature",
      "id": 1011019,
      "geometry": {
        "type": "Point",
        "coordinates": [
          152.95018052066774,
          -27.243469564502796
        ]
      },
      "properties": {
        "objectid": 1011019,
        "globalid": "{5E2BB278-248D-4970-8294-750837AC5A25}",
        "sighttime": 1715919840000,
        "joeypresent": "No",
        "numberofkoala": 1,
        "koalacondifinal": "Healthy",
        "has_attachment": null,
        "locality": null,
        "near_koala_habitat": null,
        "attachment_cc_lic_check": null,
        "lga": null,
        "sighting_lat_wgs84": null,
        "sighting_long_wgs84": null,
        "vetting_code": null
      }
    },
    {
      "type": "Feature",
      "id": 1000087,
      "geometry": {
        "type": "Point",
        "coordinates": [
          153.45554981133822,
          -28.13200972309497
        ]
      },
      "properties": {
        "objectid": 1000087,
        "globalid": "{403346B4-BA70-4C52-823A-871CC085D7AE}",
        "sighttime": 1723446420000,
        "joeypresent": "No",
        "numberofkoala": 3,
        "koalacondifinal": "Healthy",
        "has_attachment": null,
        "locality": null,
        "near_koala_habitat": null,
        "attachment_cc_lic_check": null,
        "lga": null,
        "sighting_lat_wgs84": null,
        "sighting_long_wgs84": null,
        "vetting_code": null
      }
    }
  ]
}
